Metadata-Version: 2.1
Name: colortree
Version: 0.0.5
Summary: colortree is a library that makes it easier to use colors in a terminal!
Home-page: UNKNOWN
Author: DevTree Studios
Author-email: devtreestudios@gmail.com
License: MIT
Keywords: colortree
Platform: UNKNOWN
Classifier: Development Status :: 5 - Production/Stable
Classifier: Intended Audience :: Education
Classifier: Operating System :: Microsoft :: Windows :: Windows 10
Classifier: License :: OSI Approved :: MIT License
Classifier: Programming Language :: Python :: 3
License-File: LICENCE.txt
